manga_stitcher_recoskyler/__init__.py
manga_stitcher_recoskyler/__main__.py
manga_stitcher_recoskyler/cli.py
manga_stitcher_recoskyler/manga_stitcher.py
manga_stitcher_recoskyler-1.0.0.dist-info/licenses/LICENSE
manga_stitcher_recoskyler-1.0.0.dist-info/METADATA
manga_stitcher_recoskyler-1.0.0.dist-info/WHEEL
manga_stitcher_recoskyler-1.0.0.dist-info/entry_points.txt
manga_stitcher_recoskyler-1.0.0.dist-info/top_level.txt
manga_stitcher_recoskyler-1.0.0.dist-info/RECORD
